tilos_radio_player/__init__.py
tilos_radio_player/testing.py
tilos_radio_player/tilos.py
tilos_radio_player/tilos_api_shows.py
tilos_radio_player/tilos_interactive.py
tilos_radio_player/tilos_shows.py
tilos_radio_player-0.0.4.dist-info/LICENSE
tilos_radio_player-0.0.4.dist-info/METADATA
tilos_radio_player-0.0.4.dist-info/WHEEL
tilos_radio_player-0.0.4.dist-info/entry_points.txt
tilos_radio_player-0.0.4.dist-info/top_level.txt
tilos_radio_player-0.0.4.dist-info/RECORD
